winrt/_winrt_windows_applicationmodel_background.cp313-win_amd64.pyd
winrt/_winrt_windows_applicationmodel_background.pyi
winrt/windows/applicationmodel/background/__init__.py
winrt/windows/applicationmodel/background/py.typed
winrt_windows_applicationmodel_background-3.2.1.dist-info/METADATA
winrt_windows_applicationmodel_background-3.2.1.dist-info/WHEEL
winrt_windows_applicationmodel_background-3.2.1.dist-info/top_level.txt
winrt_windows_applicationmodel_background-3.2.1.dist-info/RECORD
